setup.py
rpathology/__init__.py
rpathology/api.py
rpathology/compat.py
rpathology/elf.py
rpathology/fixer.py
rpathology/list.py
rpathology/macho.py
rpathology/show.py
rpathology.egg-info/PKG-INFO
rpathology.egg-info/SOURCES.txt
rpathology.egg-info/dependency_links.txt
rpathology.egg-info/entry_points.txt
rpathology.egg-info/top_level.txt