Metadata-Version: 1.1
Name: rpathology
Version: 0.0.6
Summary: A library for dealing with executable RPATHs
Home-page: https://github.com/jwiggins/rpathology
Author: John Wiggins
Author-email: john.wiggins@xfel.eu
License: MIT
Platform: UNKNOWN
Classifier: Development Status :: 4 - Beta
Classifier: Environment :: Console
Classifier: Intended Audience :: Developers
Classifier: License :: OSI Approved :: MIT License
Classifier: Programming Language :: Python
Classifier: Programming Language :: Python :: 2
Classifier: Programming Language :: Python :: 3
Classifier: Topic :: Software Development :: Libraries
Classifier: Operating System :: POSIX
Classifier: Operating System :: Unix
Classifier: Operating System :: MacOS
